_pyehm.cp312-win32.pyd
pyehm/__init__.py
pyehm/core.py
pyehm/net.py
pyehm/plotting.py
pyehm/utils.py
pyehm/plugins/__init__.py
pyehm/plugins/stonesoup.py
pyehm-2.0.dist-info/LICENSE
pyehm-2.0.dist-info/METADATA
pyehm-2.0.dist-info/WHEEL
pyehm-2.0.dist-info/entry_points.txt
pyehm-2.0.dist-info/top_level.txt
pyehm-2.0.dist-info/RECORD
