Metadata-Version: 2.1
Name: pyehm
Version: 2.0
Summary: Python Efficient Hypothesis Management (PyEHM)
Home-page: https://github.com/sglvladi/pyehm
Author: Lyudmil Vladimirov
Author-email: sglvladi@liverpool.ac.uk
Maintainer: University of Liverpool
Project-URL: Documentation, https://pyehm.rtfd.io/
Project-URL: Source, https://github.com/sglvladi/pyehm
Project-URL: Issue Tracker, https://github.com/sglvladi/pyehm/issues
Keywords: python,pyehm,ehm
Classifier: Development Status :: 5 - Production/Stable
Classifier: License :: OSI Approved :: Eclipse Public License 2.0 (EPL-2.0)
Classifier: Intended Audience :: Science/Research
Classifier: Topic :: Scientific/Engineering
Classifier: Programming Language :: Python :: 3 :: Only
Classifier: Operating System :: OS Independent
Requires-Python: >=3.9
License-File: LICENSE
Requires-Dist: numpy
Requires-Dist: networkx
Requires-Dist: stonesoup
Requires-Dist: setuptools>=42
Requires-Dist: pydot
Requires-Dist: matplotlib
Provides-Extra: dev
Requires-Dist: pytest-flake8; extra == "dev"
Requires-Dist: pytest-cov; extra == "dev"
Requires-Dist: flake8; extra == "dev"
Requires-Dist: sphinx; extra == "dev"
Requires-Dist: sphinx_rtd_theme; extra == "dev"
Requires-Dist: sphinx-gallery>=0.8; extra == "dev"
